MANIFEST.in
README.rst
setup.cfg
setup.py
uga/Args.py
uga/Definitions.py
uga/Fxns.py
uga/Geno.c
uga/Geno.pxd
uga/Geno.pyx
uga/Map.py
uga/Model.c
uga/Model.pyx
uga/Parse.py
uga/Process.py
uga/Qsub.py
uga/RunFilter.py
uga/RunMerge.py
uga/RunMeta.py
uga/RunSnv.py
uga/RunSnvgroup.py
uga/RunSnvgroupplot.py
uga/RunSnvplot.py
uga/RunTools.py
uga/Variant.c
uga/Variant.pxd
uga/Variant.pyx
uga/__init__.py
uga/__main__.py
uga/__version__.py
uga.egg-info/PKG-INFO
uga.egg-info/SOURCES.txt
uga.egg-info/dependency_links.txt
uga.egg-info/entry_points.txt
uga.egg-info/not-zip-safe
uga.egg-info/requires.txt
uga.egg-info/top_level.txt