Metadata-Version: 1.1
Name: uga
Version: 2.0.4
Summary: Universal Genome Analyst (uga) is a tool designed to assist biomedical researchers in complex genomic data analysis
Home-page: UNKNOWN
Author: Ryan Koesterer
Author-email: uga-feedback@gmail.com
License: UNKNOWN
Platform: UNKNOWN
Classifier: Programming Language :: Python :: 2.7
Classifier: Development Status :: 4 - Beta
Classifier: License :: OSI Approved :: GNU General Public License v3 or later (GPLv3+)
Classifier: Topic :: Scientific/Engineering :: Bio-Informatics
